mailmagician/__init__.py
mailmagician/_mailbot.py
mailmagician/_smtp_server.py
MailMagician-0.7.0.dist-info/LICENSE
MailMagician-0.7.0.dist-info/METADATA
MailMagician-0.7.0.dist-info/WHEEL
MailMagician-0.7.0.dist-info/top_level.txt
MailMagician-0.7.0.dist-info/RECORD
