Metadata-Version: 2.1
Name: MailMagician
Version: 0.7.0
Summary: A package of email robots
Home-page: https://github.com/leoxiang66/MailBot
Author: Tao Xiang
Author-email: tao.xiang@tum.de
License: UNKNOWN
Platform: UNKNOWN
Classifier: Programming Language :: Python :: 3.8
Classifier: License :: OSI Approved :: MIT License
License-File: LICENSE
